fastnbs/__init__.py
fastnbs/nbs.py
fastnbs/vis.py
fast_nbs-0.0.1.dist-info/LICENSE.txt
fast_nbs-0.0.1.dist-info/METADATA
fast_nbs-0.0.1.dist-info/WHEEL
fast_nbs-0.0.1.dist-info/top_level.txt
fast_nbs-0.0.1.dist-info/RECORD
